scportrait/__init__.py
scportrait/data/__init__.py
scportrait/data/_dataloader.py
scportrait/data/_datasets.py
scportrait/data/_single_cell_images.py
scportrait/io/__init__.py
scportrait/io/_convert.py
scportrait/io/daskmmap.py
scportrait/io/h5sc.py
scportrait/pipeline/__init__.py
scportrait/pipeline/_base.py
scportrait/pipeline/extraction.py
scportrait/pipeline/featurization.py
scportrait/pipeline/project.py
scportrait/pipeline/selection.py
scportrait/pipeline/_utils/constants.py
scportrait/pipeline/_utils/helper.py
scportrait/pipeline/_utils/sdata_io.py
scportrait/pipeline/_utils/segmentation.py
scportrait/pipeline/_utils/spatialdata_helper.py
scportrait/pipeline/mask_filtering/__init__.py
scportrait/pipeline/mask_filtering/filter_segmentation.py
scportrait/pipeline/mask_filtering/workflows.py
scportrait/pipeline/segmentation/__init__.py
scportrait/pipeline/segmentation/segmentation.py
scportrait/pipeline/segmentation/workflows/__init__.py
scportrait/pipeline/segmentation/workflows/_base_segmentation_workflow.py
scportrait/pipeline/segmentation/workflows/_cellpose.py
scportrait/pipeline/segmentation/workflows/_model_caches.py
scportrait/pipeline/segmentation/workflows/_wga_segmentation.py
scportrait/plotting/__init__.py
scportrait/plotting/_utils.py
scportrait/plotting/h5sc.py
scportrait/plotting/sdata.py
scportrait/plotting/vis.py
scportrait/processing/__init__.py
scportrait/processing/images/__init__.py
scportrait/processing/images/_image_processing.py
scportrait/processing/images/_zstack_compression.py
scportrait/processing/masks/__init__.py
scportrait/processing/masks/mask_filtering.py
scportrait/tools/__init__.py
scportrait/tools/h5sc/__init__.py
scportrait/tools/h5sc/operations.py
scportrait/tools/ml/__init__.py
scportrait/tools/ml/callback.py
scportrait/tools/ml/datasets.py
scportrait/tools/ml/metrics.py
scportrait/tools/ml/models.py
scportrait/tools/ml/plmodels.py
scportrait/tools/ml/pretrained_models.py
scportrait/tools/ml/transforms.py
scportrait-1.5.1.dist-info/licenses/LICENSE
scportrait-1.5.1.dist-info/METADATA
scportrait-1.5.1.dist-info/WHEEL
scportrait-1.5.1.dist-info/top_level.txt
scportrait-1.5.1.dist-info/RECORD
