Metadata-Version: 2.4
Name: scportrait
Version: 1.5.1
Summary: Computational framework to generate single cell datasets from raw microscopy images.
Author: Altana Namsaraeva, Georg Wallmann
Author-email: Sophia Maedler <hello@sophia-maedler.com>, Niklas Schmacke <niklas@schmacke.bio>
Maintainer-email: Sophia Maedler <hello@sophia-maedler.com>
License:                                  Apache License
Project-URL: Homepage, https://github.com/MannLabs/scPortrait
Project-URL: Documentation, https://mannlabs.github.io/scPortrait/html/index.html
Project-URL: Source, https://github.com/MannLabs/scPortrait
Keywords: single-cell,image analysis,spatial omics,deep learning,image representation
Classifier: License :: OSI Approved :: Apache Software License
Classifier: Development Status :: 4 - Beta
Classifier: Programming Language :: Python
Classifier: Intended Audience :: Science/Research
Classifier: Natural Language :: English
Classifier: Operating System :: MacOS :: MacOS X
Classifier: Operating System :: POSIX :: Linux
Classifier: Topic :: Scientific/Engineering :: Bio-Informatics
Requires-Python: >=3.10
License-File: LICENSE
Requires-Dist: tqdm
Requires-Dist: psutil
Requires-Dist: numba
Requires-Dist: h5py
Requires-Dist: alphabase
Requires-Dist: anndata<0.12
Requires-Dist: spatialdata<0.6,>=0.3.0
Requires-Dist: pyarrow<22.0.0
Requires-Dist: py-lmd>=1.3.1
Requires-Dist: spatialdata-plot<=0.2.11
Requires-Dist: matplotlib
Requires-Dist: tifffile
Requires-Dist: zarr
Requires-Dist: ome-zarr
Requires-Dist: scipy
Requires-Dist: scikit-image>=0.22.0
Requires-Dist: scikit-learn
Requires-Dist: mahotas
Requires-Dist: scikit-fmm
Requires-Dist: cellpose<4,>=3.1.1
Requires-Dist: torch
Requires-Dist: pytorch-lightning
Requires-Dist: torchvision
Provides-Extra: dev
Requires-Dist: pre-commit; extra == "dev"
Provides-Extra: tests
Requires-Dist: pytest; extra == "tests"
Provides-Extra: docs
Requires-Dist: sphinx; extra == "docs"
Requires-Dist: sphinx-argparse; extra == "docs"
Requires-Dist: sphinx-rtd-theme==2.0.0; extra == "docs"
Requires-Dist: nbsphinx; extra == "docs"
Requires-Dist: nbsphinx-link; extra == "docs"
Requires-Dist: sphinx-book-theme; extra == "docs"
Requires-Dist: sphinx-design; extra == "docs"
Requires-Dist: sphinx-copybutton; extra == "docs"
Requires-Dist: sphinx-gallery; extra == "docs"
Provides-Extra: plotting
Requires-Dist: napari-spatialdata; extra == "plotting"
Requires-Dist: pyqt5; extra == "plotting"
Requires-Dist: matplotlib_scalebar; extra == "plotting"
Requires-Dist: spatialdata-plot; extra == "plotting"
Provides-Extra: stitching
Requires-Dist: ashlar>=1.19.0; extra == "stitching"
Requires-Dist: networkx; extra == "stitching"
Requires-Dist: seaborn; extra == "stitching"
Requires-Dist: yattag; extra == "stitching"
Provides-Extra: convnext
Requires-Dist: transformers>=4.44.2; extra == "convnext"
Provides-Extra: all
Requires-Dist: pre-commit; extra == "all"
Requires-Dist: pytest; extra == "all"
Requires-Dist: sphinx; extra == "all"
Requires-Dist: sphinx-argparse; extra == "all"
Requires-Dist: sphinx-rtd-theme==2.0.0; extra == "all"
Requires-Dist: nbsphinx; extra == "all"
Requires-Dist: nbsphinx-link; extra == "all"
Requires-Dist: sphinx-book-theme; extra == "all"
Requires-Dist: sphinx-design; extra == "all"
Requires-Dist: sphinx-copybutton; extra == "all"
Requires-Dist: sphinx-gallery; extra == "all"
Requires-Dist: napari-spatialdata; extra == "all"
Requires-Dist: pyqt5; extra == "all"
Requires-Dist: matplotlib_scalebar; extra == "all"
Requires-Dist: spatialdata-plot; extra == "all"
Requires-Dist: ashlar>=1.19.0; extra == "all"
Requires-Dist: networkx; extra == "all"
Requires-Dist: seaborn; extra == "all"
Requires-Dist: yattag; extra == "all"
Dynamic: license-file
